textxirirefs/__init__.py
textxirirefs/exceptions.py
textxirirefs/iri.py
textxirirefs/iri.tx
textxirirefs/scripts.py
textxirirefs/uri.py
textxirirefs/uri.tx
textx_lang_irirefs-0.0.dev8.dist-info/LICENSE
textx_lang_irirefs-0.0.dev8.dist-info/METADATA
textx_lang_irirefs-0.0.dev8.dist-info/WHEEL
textx_lang_irirefs-0.0.dev8.dist-info/entry_points.txt
textx_lang_irirefs-0.0.dev8.dist-info/top_level.txt
textx_lang_irirefs-0.0.dev8.dist-info/RECORD
